linearwinvolume
